aifs/__init__.py
aifs/search.py
aifs/test.py
aifs/testfuncs/_.aifs
aifs/testfuncs/bookTicket.py
aifs/testfuncs/browseWeb.py
aifs/testfuncs/cookDish.py
aifs/testfuncs/doLaundry.py
aifs/testfuncs/drinkAlcohol.py
aifs/testfuncs/executiveAssistant.py
aifs/testfuncs/liftWeights.py
aifs/testfuncs/lowerBrightness.py
aifs/testfuncs/playTennis.py
aifs/testfuncs/sendEmail.py
aifs/testfuncs/setAlarm.py
aifs-0.0.16.dist-info/LICENSE
aifs-0.0.16.dist-info/METADATA
aifs-0.0.16.dist-info/WHEEL
aifs-0.0.16.dist-info/RECORD
