Metadata-Version: 2.1
Name: aifs
Version: 0.0.16
Summary: Local semantic search. Stupidly simple.
License: MIT
Author: Killian Lucas
Author-email: killian@openinterpreter.com
Requires-Python: >=3.9,<4
Classifier: License :: OSI Approved :: MIT License
Classifier: Programming Language :: Python :: 3
Classifier: Programming Language :: Python :: 3.9
Classifier: Programming Language :: Python :: 3.10
Classifier: Programming Language :: Python :: 3.11
Classifier: Programming Language :: Python :: 3.12
